spmysql/__init__.py
spmysql-1.0.1.dist-info/LICENSE.txt
spmysql-1.0.1.dist-info/METADATA
spmysql-1.0.1.dist-info/WHEEL
spmysql-1.0.1.dist-info/entry_points.txt
spmysql-1.0.1.dist-info/top_level.txt
spmysql-1.0.1.dist-info/RECORD
