Metadata-Version: 2.1
Name: spmysql
Version: 1.0.1
Summary: A Python package to work with mysql database.
Home-page: https://github.com/suryaprakash0831/sp_mysql
Author: Suryaprakash S
Author-email: suryaprakash0831@gmail.com
License: MIT
Platform: UNKNOWN
Classifier: License :: OSI Approved :: MIT License
Classifier: Programming Language :: Python :: 3
Classifier: Programming Language :: Python :: 3.7
Requires-Dist: requests
